pyecharts_plus/__init__.py
pyecharts_plus/charts/__init__.py
pyecharts_plus/charts/bubble_4D.py
pyecharts_plus/charts/color_map.py
pyecharts_plus/charts/geo_arcs.py
pyecharts_plus/charts/map_bin.py
pyecharts_plus/charts/map_bin_bubble.py
pyecharts_plus/charts/map_bin_scatter.py
pyecharts_plus/charts/warehouse_sketch.py
pyecharts_plus/datasets/__init__.py
pyecharts_plus/datasets/city_center_point_coords.json
pyecharts_plus/datasets/city_polygon_coords.json
pyecharts_plus/datasets/coordinates.py
pyecharts_plus-0.1.7.dist-info/DESCRIPTION.rst
pyecharts_plus-0.1.7.dist-info/METADATA
pyecharts_plus-0.1.7.dist-info/RECORD
pyecharts_plus-0.1.7.dist-info/WHEEL
pyecharts_plus-0.1.7.dist-info/metadata.json
pyecharts_plus-0.1.7.dist-info/top_level.txt
